mash/__init__.py
mash/cloud/__init__.py
mash/cloud/file_exists.py
mash/cloud/file_exists_test.py
mash/cloud/glob.py
mash/cloud/glob_test.py
mash/images/__init__.py
mash/images/conversion.py
mash/images/conversion_test.py
mash/images/crop.py
mash/images/crop_test.py
mash/images/normalization.py
mash/images/normalization_test.py
mash/images/resize.py
mash/images/resize_test.py
mash/images/tile.py
mash/images/tile_test.py
mash/images/truecolor.py
mash/images/truecolor_test.py
mash/ui/__init__.py
mash/ui/console.py
mash/ui/logs.py
mash/ui/logs_test.py
mashlib-0.1.9.dist-info/METADATA
mashlib-0.1.9.dist-info/WHEEL
mashlib-0.1.9.dist-info/RECORD
