Metadata-Version: 2.1
Name: mashlib
Version: 0.1.9
Summary: Common library tools for Moonshine AI
Home-page: https://github.com/moonshinelabs-ai/mash
License: MIT
Keywords: moonshine,library
Author: Nate Harada
Author-email: mash@moonshinelabs.ai
Requires-Python: >=3.10,<4.0
Classifier: License :: OSI Approved :: MIT License
Classifier: Programming Language :: Python :: 3
Classifier: Programming Language :: Python :: 3.10
Classifier: Programming Language :: Python :: 3.11
Classifier: Programming Language :: Python :: 3.12
Classifier: Programming Language :: Python :: 3.13
Requires-Dist: boto3 (>=1.35.81)
Requires-Dist: loguru (>=0.7.3)
Requires-Dist: moto (>=4.2.14)
Requires-Dist: numpy (>=1.26.4)
Requires-Dist: pillow (>=11.0.0)
Requires-Dist: pillow-heif (>=0.21.0)
Requires-Dist: requests (>=2.32.3)
Requires-Dist: rich (>=13.9.4)
Requires-Dist: scikit-image (>=0.22.0)
Requires-Dist: smart-open (>=6.4.0)
Requires-Dist: torch (>=2.0.0,!=2.0.1,!=2.1.0)
Project-URL: Repository, https://github.com/moonshinelabs-ai/mash
